django_ldap_sync-0.5.0.dist-info/DESCRIPTION.rst
django_ldap_sync-0.5.0.dist-info/METADATA
django_ldap_sync-0.5.0.dist-info/RECORD
django_ldap_sync-0.5.0.dist-info/WHEEL
django_ldap_sync-0.5.0.dist-info/metadata.json
django_ldap_sync-0.5.0.dist-info/top_level.txt
ldap_sync/__init__.py
ldap_sync/callbacks.py
ldap_sync/search.py
ldap_sync/settings.py
ldap_sync/sync.py
ldap_sync/tasks.py
ldap_sync/management/__init__.py
ldap_sync/management/commands/__init__.py
ldap_sync/management/commands/syncldap.py
ldap_sync/tests/__init__.py
ldap_sync/tests/settings.py
ldap_sync/tests/test_settings.py
ldap_sync/tests/test_sync.py
