Metadata-Version: 2.0
Name: django-ldap-sync
Version: 0.5.0
Summary: A Django application for synchronizing LDAP users and groups
Home-page: https://github.com/jbittel/django-ldap-sync
Author: Jason Bittel
Author-email: jason.bittel@gmail.com
License: BSD
Download-URL: https://github.com/jbittel/django-ldap-sync
Keywords: django,ldap,active directory,synchronize,sync
Platform: UNKNOWN
Classifier: Development Status :: 3 - Alpha
Classifier: Environment :: Web Environment
Classifier: Programming Language :: Python
Classifier: Framework :: Django
Classifier: Intended Audience :: Developers
Classifier: License :: OSI Approved :: BSD License
Classifier: Operating System :: OS Independent
Classifier: Topic :: Software Development :: Libraries :: Python Modules
Classifier: Topic :: System :: Systems Administration :: Authentication/Directory
Requires-Dist: python-ldap (>=2.4.13)
